setup.py
probability_distributions_2023/Binomialdistribution.py
probability_distributions_2023/Gaussiandistribution.py
probability_distributions_2023/Generaldistribution.py
probability_distributions_2023/__init__.py
probability_distributions_2023.egg-info/PKG-INFO
probability_distributions_2023.egg-info/SOURCES.txt
probability_distributions_2023.egg-info/dependency_links.txt
probability_distributions_2023.egg-info/not-zip-safe
probability_distributions_2023.egg-info/top_level.txt