Metadata-Version: 1.0
Name: probability-distributions-2023
Version: 0.1
Summary: Gaussian and Binomial distributions
Home-page: UNKNOWN
Author: Karankumar Patel
Author-email: patelkaran0496@gmail.com
License: UNKNOWN
Platform: UNKNOWN
